README.md
setup.cfg
setup.py
Topsis_RiaSoam_101803258.egg-info/PKG-INFO
Topsis_RiaSoam_101803258.egg-info/SOURCES.txt
Topsis_RiaSoam_101803258.egg-info/dependency_links.txt
Topsis_RiaSoam_101803258.egg-info/requires.txt
Topsis_RiaSoam_101803258.egg-info/top_level.txt
topsis_pckg/__init__.py
topsis_pckg/topsis.py