Metadata-Version: 2.1
Name: Topsis-RiaSoam-101803258
Version: 0.0.6
Summary: it is package which tells you best value based on the data by applying accurate mathematics functions
Home-page: https://github.com/ria-2511/topsis_pckg
Author: Ria Soam
Author-email: rsoam_be18@thapar.edu
License: UNKNOWN
Platform: UNKNOWN
Classifier: Programming Language :: Python :: 3
Classifier: License :: OSI Approved :: MIT License
Classifier: Operating System :: OS Independent
Requires-Python: >=3.6
